{"file:///d%3A/Desktop/modrn/package-lock.json":{"language":"JSON","code":6,"comment":0,"blank":1},"file:///d%3A/Desktop/modrn/README.md":{"language":"Markdown","code":30,"comment":0,"blank":8},"file:///d%3A/Desktop/modrn/frontend/index.html":{"language":"HTML","code":267,"comment":14,"blank":37},"file:///d%3A/Desktop/modrn/backend/package.json":{"language":"JSON","code":22,"comment":0,"blank":0},"file:///d%3A/Desktop/modrn/frontend/admin.html":{"language":"HTML","code":157,"comment":8,"blank":20},"file:///d%3A/Desktop/modrn/frontend/shop.html":{"language":"HTML","code":105,"comment":9,"blank":14},"file:///d%3A/Desktop/modrn/frontend/js/index.js":{"language":"JavaScript","code":116,"comment":29,"blank":38},"file:///d%3A/Desktop/modrn/frontend/js/shop.js":{"language":"JavaScript","code":270,"comment":30,"blank":78},"file:///d%3A/Desktop/modrn/frontend/js/admin.js":{"language":"JavaScript","code":190,"comment":16,"blank":35},"file:///d%3A/Desktop/modrn/backend/db.js":{"language":"JavaScript","code":20,"comment":0,"blank":3},"file:///d%3A/Desktop/modrn/frontend/style.css":{"language":"PostCSS","code":1969,"comment":89,"blank":289},"file:///d%3A/Desktop/modrn/backend/package-lock.json":{"language":"JSON","code":1157,"comment":0,"blank":1},"file:///d%3A/Desktop/modrn/backend/server.js":{"language":"JavaScript","code":191,"comment":17,"blank":61},"file:///d%3A/Desktop/modrn/docs/style.css":{"language":"PostCSS","code":1969,"comment":89,"blank":289},"file:///d%3A/Desktop/modrn/docs/js/index.js":{"language":"JavaScript","code":116,"comment":29,"blank":38},"file:///d%3A/Desktop/modrn/docs/admin.html":{"language":"HTML","code":157,"comment":8,"blank":20},"file:///d%3A/Desktop/modrn/docs/shop.html":{"language":"HTML","code":105,"comment":9,"blank":14},"file:///d%3A/Desktop/modrn/docs/js/admin.js":{"language":"JavaScript","code":190,"comment":16,"blank":35},"file:///d%3A/Desktop/modrn/docs/js/shop.js":{"language":"JavaScript","code":270,"comment":30,"blank":78},"file:///d%3A/Desktop/modrn/docs/index.html":{"language":"HTML","code":267,"comment":14,"blank":37},"file:///d%3A/Desktop/modrn/backend/.env":{"language":"Dotenv","code":8,"comment":0,"blank":2}}